text_fancipy/__init__.py
text_fancipy/__main__.py
text_fancipy/fancipy.py
text_fancipy-1.4.1.dist-info/LICENSE.txt
text_fancipy-1.4.1.dist-info/METADATA
text_fancipy-1.4.1.dist-info/WHEEL
text_fancipy-1.4.1.dist-info/entry_points.txt
text_fancipy-1.4.1.dist-info/top_level.txt
text_fancipy-1.4.1.dist-info/RECORD
