Metadata-Version: 2.1
Name: text-fancipy
Version: 1.4.1
Summary: Python tool for converting all plain English letters in text into various fancy-styled text and back
Home-page: https://pypi.org/project/text-fancipy/
Author: Adam Twardoch
Author-email: adam+github@twardoch.com
License: Apache-2.0
Project-URL: Documentation, https://github.com/twardoch/text_fancipy
Project-URL: Source, https://github.com/twardoch/text_fancipy
Platform: any
Classifier: Development Status :: 4 - Beta
Classifier: Programming Language :: Python :: 3.9
Classifier: Topic :: Text Processing
Classifier: Topic :: Text Processing :: Filters
Classifier: Topic :: Text Processing :: Linguistic
Requires-Python: >=3.9
License-File: LICENSE.txt
Requires-Dist: fire
Requires-Dist: unicodedata2
Provides-Extra: testing
Requires-Dist: setuptools ; extra == 'testing'
Requires-Dist: pytest ; extra == 'testing'
Requires-Dist: pytest-cov ; extra == 'testing'
